<?xml version="1.0" encoding="UTF-8"?>
<!-- <!DOCTYPE dwr PUBLIC "-//GetAhead Limited//DTD Direct Web Remoting 2.0//EN" "http://getahead.ltd.uk/dwr/dwr20.dtd"> -->
<!DOCTYPE dwr PUBLIC "-//GetAhead Limited//DTD Direct Web Remoting 3.0//EN" "http://getahead.org/dwr//dwr30.dtd">

<dwr>

	<allow>
		<!-- ========================= SERVICE ======================== -->
		<convert converter="bean" match="com.zianedu.lms.service.UserService"/>
		<create creator="spring" javascript="userService">
			<param name="class" value="com.zianedu.lms.service.UserService"/>
			<param name="beanName" value="userService" />
		</create>

		<convert converter="bean" match="com.zianedu.lms.service.LoginService"/>
		<create creator="spring" javascript="loginService">
			<param name="class" value="com.zianedu.lms.service.LoginService"/>
			<param name="beanName" value="loginService" />
		</create>

		<convert converter="bean" match="com.zianedu.lms.service.DataManageService"/>
		<create creator="spring" javascript="dataManageService">
			<param name="class" value="com.zianedu.lms.service.DataManageService"/>
			<param name="beanName" value="dataManageService" />
		</create>

		<convert converter="bean" match="com.zianedu.lms.service.SelectboxService"/>
		<create creator="spring" javascript="selectboxService">
			<param name="class" value="com.zianedu.lms.service.SelectboxService"/>
			<param name="beanName" value="selectboxService" />
		</create>

		<convert converter="bean" match="com.zianedu.lms.service.ProductManageService"/>
		<create creator="spring" javascript="productManageService">
			<param name="class" value="com.zianedu.lms.service.ProductManageService"/>
			<param name="beanName" value="productManageService" />
		</create>

		<!-- ========================= MANAGER ======================== -->

		<!--  vo 선언 -->
		<convert converter="bean" match="com.zianedu.lms.vo.TUserVO"/>
		<convert converter="bean" match="com.zianedu.lms.vo.TCategoryVO"/>
		<convert converter="bean" match="com.zianedu.lms.vo.TCategoryOtherInfoVO"/>
		<convert converter="bean" match="com.zianedu.lms.vo.TSiteVO"/>
		<convert converter="bean" match="com.zianedu.lms.vo.TScheduleVO"/>
		<convert converter="bean" match="com.zianedu.lms.vo.SearchKeywordDomainVO"/>
		<convert converter="bean" match="com.zianedu.lms.vo.TSearchKeywordVO"/>
		<convert converter="bean" match="com.zianedu.lms.vo.TGoodsVO"/>
		<convert converter="bean" match="com.zianedu.lms.vo.TGoodsPriceOptionVO"/>
		<convert converter="bean" match="com.zianedu.lms.vo.TLecVO"/>
		<convert converter="bean" match="com.zianedu.lms.vo.TLecCurri"/>
		<convert converter="bean" match="com.zianedu.lms.vo.TLinkKeyVO"/>
		<convert converter="bean" match="com.zianedu.lms.vo.TGoodTeacherLinkVO"/>
		<convert converter="bean" match="com.zianedu.lms.vo.TExamMasterVO"/>
		<convert converter="bean" match="com.zianedu.lms.vo.TBookVO"/>
		<convert converter="bean" match="com.zianedu.lms.vo.TResVO"/>
		<convert converter="bean" match="com.zianedu.lms.vo.TExamQuestionBankSubjectVO"/>.
		<convert converter="bean" match="com.zianedu.lms.vo.TBankSubjectExamLinkVO"/>
		<convert converter="bean" match="com.zianedu.lms.vo.TExamQuestionBankVO"/>
        <convert converter="bean" match="com.zianedu.lms.vo.ProblemBankSearchVO"/>


		<!--  dto 선언 -->
		<convert converter="bean" match="com.zianedu.lms.dto.ResultDTO"/>
		<convert converter="bean" match="com.zianedu.lms.dto.VideoListDTO"/>
		<convert converter="bean" match="com.zianedu.lms.dto.SelectboxDTO"/>
		<convert converter="bean" match="com.zianedu.lms.dto.PagingSearchDTO"/>
		<convert converter="bean" match="com.zianedu.lms.dto.ProductDetailInfoDTO"/>
		<convert converter="bean" match="com.zianedu.lms.dto.BookDetailInfoDTO"/>
		<convert converter="bean" match="com.zianedu.lms.dto.MokExamInfoDTO"/>
		<convert converter="bean" match="com.zianedu.lms.dto.ExamDetailInfoDTO"/>
		<convert converter="bean" match="com.zianedu.lms.dto.ProblemBankListDTO"/>
		<convert converter="bean" match="com.zianedu.lms.dto.ProblemBankSubjectDTO"/>
		<convert converter="bean" match="com.zianedu.lms.dto.ProblemBankSubjectDetailDTO"/>

	</allow>

</dwr>
